ddeutil/extensions/__about__.py
ddeutil/extensions/__init__.py
ddeutil/extensions/__types.py
ddeutil/extensions/conn.py
ddeutil/extensions/dataset.py
ddeutil/extensions/exceptions.py
ddeutil/extensions/datasets/__init__.py
ddeutil/extensions/datasets/aws.py
ddeutil/extensions/datasets/minio.py
ddeutil/extensions/datasets/pl.py
ddeutil/extensions/datasets/sftp.py
ddeutil/extensions/models/__base.py
ddeutil/extensions/models/__enums.py
ddeutil/extensions/models/__init__.py
ddeutil/extensions/models/__types.py
ddeutil/extensions/models/action.py
ddeutil/extensions/models/conn.py
ddeutil/extensions/models/const.py
ddeutil/extensions/models/dtype.py
ddeutil/extensions/models/lineage.py
ddeutil/extensions/models/utils.py
ddeutil/extensions/models/datasets/__init__.py
ddeutil/extensions/models/datasets/col.py
ddeutil/extensions/models/datasets/db.py
ddeutil/extensions/models/datasets/file.py
ddeutil/extensions/models/examples/__init__.py
ddeutil/extensions/models/examples/annotated.py
ddeutil/extensions/tasks/__init__.py
ddeutil/extensions/tasks/pd_utils.py
ddeutil/extensions/tasks/pl_tasks.py
ddeutil_extensions-0.0.1.dist-info/LICENSE
ddeutil_extensions-0.0.1.dist-info/METADATA
ddeutil_extensions-0.0.1.dist-info/WHEEL
ddeutil_extensions-0.0.1.dist-info/top_level.txt
ddeutil_extensions-0.0.1.dist-info/RECORD
