Metadata-Version: 2.2
Name: ddeutil-extensions
Version: 0.0.1
Summary: Extension functions and objects
Author-email: ddeutils <korawich.anu@gmail.com>
License: MIT
Project-URL: Homepage, https://github.com/ddeutils/ddeutil-extensions/
Project-URL: Source Code, https://github.com/ddeutils/ddeutil-extensions/
Keywords: extensions,utility
Classifier: Topic :: Utilities
Classifier: Natural Language :: English
Classifier: Development Status :: 3 - Alpha
Classifier: Intended Audience :: Developers
Classifier: Operating System :: OS Independent
Classifier: Programming Language :: Python
Classifier: Programming Language :: Python :: 3 :: Only
Classifier: Programming Language :: Python :: 3.9
Classifier: Programming Language :: Python :: 3.10
Classifier: Programming Language :: Python :: 3.11
Classifier: Programming Language :: Python :: 3.12
Classifier: Programming Language :: Python :: 3.13
Requires-Python: >=3.9.13
License-File: LICENSE
Requires-Dist: fmtutil
Requires-Dist: ddeutil-workflow
Provides-Extra: test
Requires-Dist: python-dotenv==1.0.1; extra == "test"
Requires-Dist: sqlalchemy==2.0.38; extra == "test"
Requires-Dist: fsspec==2024.6.1; extra == "test"
Requires-Dist: ddeutil-extensions[aws,polars,sftp]; extra == "test"
Provides-Extra: polars
Requires-Dist: polars==0.20.31; extra == "polars"
Requires-Dist: pyarrow==17.0.0; extra == "polars"
Provides-Extra: sftp
Requires-Dist: paramiko==3.4.0; extra == "sftp"
Requires-Dist: sshtunnel==0.4.0; extra == "sftp"
Provides-Extra: aws
Requires-Dist: boto3==1.34.151; extra == "aws"
